simulatingrisk/__init__.py
simulatingrisk/about_app.md
simulatingrisk/app.py
simulatingrisk/batch_run.py
simulatingrisk/utils.py
simulatingrisk/charts/histogram.js
simulatingrisk/charts/histogram.py
simulatingrisk/hawkdove/README.md
simulatingrisk/hawkdove/app.py
simulatingrisk/hawkdove/model.py
simulatingrisk/hawkdove/run.py
simulatingrisk/hawkdove/server.py
simulatingrisk/hawkdovemulti/README.md
simulatingrisk/hawkdovemulti/analysis_utils.py
simulatingrisk/hawkdovemulti/app.py
simulatingrisk/hawkdovemulti/batch_run.py
simulatingrisk/hawkdovemulti/model.py
simulatingrisk/hawkdovemulti/run_simulation.ipynb
simulatingrisk/hawkdovemulti/simrisk_batch.slurm
simulatingrisk/risky_bet/README.md
simulatingrisk/risky_bet/app.py
simulatingrisk/risky_bet/model.py
simulatingrisk/risky_bet/run.py
simulatingrisk/risky_bet/server.py
simulatingrisk/risky_food/README.md
simulatingrisk/risky_food/__init__.py
simulatingrisk/risky_food/app.py
simulatingrisk/risky_food/model.py
simulatingrisk/risky_food/run.py
simulatingrisk/risky_food/server.py
simulatingrisk/stag_hunt/README.md
simulatingrisk/stag_hunt/__init__.py
simulatingrisk/stag_hunt/model.py
simulatingrisk/stag_hunt/run.py
simulatingrisk-1.0.0.post1.dist-info/licenses/LICENSE
simulatingrisk-1.0.0.post1.dist-info/METADATA
simulatingrisk-1.0.0.post1.dist-info/WHEEL
simulatingrisk-1.0.0.post1.dist-info/entry_points.txt
simulatingrisk-1.0.0.post1.dist-info/top_level.txt
simulatingrisk-1.0.0.post1.dist-info/RECORD
