Metadata-Version: 2.4
Name: simulatingrisk
Version: 1.0.0.post1
Summary: Agent-based modeling for simulations related to risk and rationality
License: Apache-2
Classifier: Programming Language :: Python :: 3
Requires-Python: >=3.7
License-File: LICENSE
Requires-Dist: mesa==2.1.5
Requires-Dist: matplotlib
Requires-Dist: altair>5.0.1
Provides-Extra: dev
Requires-Dist: pre-commit; extra == "dev"
Requires-Dist: pytest; extra == "dev"
Requires-Dist: pytest-cov; extra == "dev"
Provides-Extra: analysis
Requires-Dist: jupyterlab; extra == "analysis"
Requires-Dist: polars; extra == "analysis"
Requires-Dist: hvplot; extra == "analysis"
Requires-Dist: pyarrow; extra == "analysis"
Requires-Dist: altair; extra == "analysis"
Requires-Dist: scipy; extra == "analysis"
Requires-Dist: scikit-learn; extra == "analysis"
Requires-Dist: seaborn; extra == "analysis"
Requires-Dist: vegafusion[embed]>=1.5.0; extra == "analysis"
Requires-Dist: vl-convert-python; extra == "analysis"
Requires-Dist: great-tables; extra == "analysis"
Dynamic: license-file
